discordembedmarkup/__init__.py
discordembedmarkup/parse.py
discordembedmarkup/util.py
discordembedmarkup-1.0.0.dist-info/LICENSE
discordembedmarkup-1.0.0.dist-info/METADATA
discordembedmarkup-1.0.0.dist-info/WHEEL
discordembedmarkup-1.0.0.dist-info/top_level.txt
discordembedmarkup-1.0.0.dist-info/RECORD
