Metadata-Version: 2.1
Name: discordembedmarkup
Version: 1.0.0
Summary: Declarative Discord Embeds
Home-page: https://github.com/xImAnton/Discord-Embed-Markup
Author: xImAnton_
License: UNKNOWN
Project-URL: Bug Tracker, https://github.com/xImAnton/Discord-Embed-Markup/issues
Platform: UNKNOWN
Classifier: Programming Language :: Python :: 3
Classifier: License :: OSI Approved :: GNU General Public License v3 (GPLv3)
Classifier: Operating System :: OS Independent
Requires-Python: >=3.8
License-File: LICENSE
